dash_transcrypt/__init__.py
dash_transcrypt/transpile.py
dash_transcrypt-0.0.6.dist-info/METADATA
dash_transcrypt-0.0.6.dist-info/WHEEL
dash_transcrypt-0.0.6.dist-info/top_level.txt
dash_transcrypt-0.0.6.dist-info/RECORD
