Metadata-Version: 2.1
Name: dash-transcrypt
Version: 0.0.6
Summary: Transcrypt bindings for Plotly Dash.
Home-page: https://github.com/thedirtyfew/dash-transcrypt/
Author: Emil Haldrup Eriksen
License: MIT
Platform: UNKNOWN
Classifier: Programming Language :: Python :: 3
Classifier: Framework :: Dash
Requires-Dist: transcrypt
